src/__init__.py
src/cli.py
src/commands/__init__.py
src/commands/config.py
src/commands/enums.py
src/commands/pipelines.py
src/commands/project.py
src/commands/server.py
src/common/__init__.py
src/common/base_enum.py
src/common/context.py
src/common/decorators.py
src/common/template.py
src/constants.py
src/errors.py
src/templates/crontab_le.sh
src/templates/database.sh
src/templates/django_nginx.conf
src/templates/django_nginx_ssl.conf
src/templates/django_supervisor.conf
src/templates/haproxy.cfg
src/templates/post-receive
src/templates/renew_le.sh
src/templates/start.sh
src/templates/static_web.conf
src/templates/system-bionic.txt
src/templates/system-focal.txt
src/templates/system-trusty.txt
src/templates/system-xenial.txt
src/templates/system.sh
tests/__init__.py
tests/test_config.py
tests/test_pipelines.py
tests/test_project.py
tests/test_server.py
tests/test_utils.py
wise_cli-0.0.4.dist-info/entry_points.txt
wise_cli-0.0.4.dist-info/LICENSE
wise_cli-0.0.4.dist-info/WHEEL
wise_cli-0.0.4.dist-info/METADATA
wise_cli-0.0.4.dist-info/RECORD
