Metadata-Version: 2.1
Name: wise-cli
Version: 0.0.4
Summary: Django deployments CLI.
Home-page: https://github.com/victoraguilarc/wise-cli/
License: MIT
Keywords: Django,Deployment,Poetry
Author: Victor Aguilar C.
Author-email: vicobits@gmail.com
Maintainer: Victor Aguilar C.
Maintainer-email: vicobits@gmail.com
Requires-Python: >=3.8,<4.0
Classifier: License :: OSI Approved :: MIT License
Classifier: Programming Language :: Python :: 3
Classifier: Programming Language :: Python :: 3.10
Classifier: Programming Language :: Python :: 3.8
Classifier: Programming Language :: Python :: 3.9
Requires-Dist: Jinja2 (>=3.1.1,<4.0.0)
Requires-Dist: click (==8.1.2)
Requires-Dist: fabric
Requires-Dist: requests (>=2.27.1,<3.0.0)
Project-URL: Documentation, https://github.com/victoraguilarc/wise-cli/
Project-URL: Repository, https://github.com/victoraguilarc/wise-cli/
Project-URL: issues, https://github.com/hackersandslackers/python-poetry-tutorial/issues
